pyxel_reload/__init__.py
pyxel_reload-0.2.2.dist-info/METADATA
pyxel_reload-0.2.2.dist-info/WHEEL
pyxel_reload-0.2.2.dist-info/entry_points.txt
pyxel_reload-0.2.2.dist-info/licenses/LICENSE
pyxel_reload-0.2.2.dist-info/RECORD
