Metadata-Version: 2.4
Name: pyxel-reload
Version: 0.2.2
Summary: Run your pyxel applications, reloading when code / assets change
Author: Reiner Gerecke
License: MIT License
License-File: LICENSE
Requires-Python: >=3.10
Requires-Dist: pyxel>=2.2
Requires-Dist: watchfiles>=1.0.3
